README.rst
setup.py
dubbo_zookeeper_thrift/__init__.py
dubbo_zookeeper_thrift/base_thrift_client.py
dubbo_zookeeper_thrift/dubbo_thrift_manager.py
dubbo_zookeeper_thrift/dubbo_zk_manager.py
dubbo_zookeeper_thrift.egg-info/PKG-INFO
dubbo_zookeeper_thrift.egg-info/SOURCES.txt
dubbo_zookeeper_thrift.egg-info/dependency_links.txt
dubbo_zookeeper_thrift.egg-info/top_level.txt
dubbo_zookeeper_thrift.egg-info/zip-safe