Metadata-Version: 1.1
Name: dubbo-zookeeper-thrift
Version: 1.0.1
Summary: a python liberaries  for dubbo_zookeeper_thrift tutorial.
Home-page: http://www.rocyuan.com
Author: rocyuan
Author-email: admin@rocyuan.com
License: MIT
Keywords: python wechat dubbo_zookeeper_thrift api
Platform: UNKNOWN
Classifier: License :: OSI Approved :: MIT License
Classifier: Programming Language :: Python
Classifier: Intended Audience :: Developers
Classifier: Operating System :: OS Independent
